pynosqlite/__init__.py
pynosqlite-0.2.dist-info/LICENSE.txt
pynosqlite-0.2.dist-info/METADATA
pynosqlite-0.2.dist-info/WHEEL
pynosqlite-0.2.dist-info/top_level.txt
pynosqlite-0.2.dist-info/RECORD
