Metadata-Version: 2.1
Name: pynosqlite
Version: 0.2
Summary: Fast and Lightweight json file based database
Home-page: https://github.com/programmingplanet/pynosqlite
Author: Moin Ahmad
Author-email: ahmadmoin723@gmail.com
License: MIT
Download-URL: https://github.com/ProgrammingPlanet/pynosqlite/archive/refs/tags/v0.2.tar.gz
Keywords: Single File,Json,DataBase,Small,LightWeight,Fast
Platform: UNKNOWN
Classifier: Development Status :: 3 - Alpha
Classifier: Intended Audience :: Developers
Classifier: Topic :: Software Development :: Build Tools
Classifier: License :: OSI Approved :: MIT License
Classifier: Programming Language :: Python :: 3.9
Classifier: Programming Language :: Python :: 3.8
Classifier: Programming Language :: Python :: 3.7
Classifier: Programming Language :: Python :: 3.6
License-File: LICENSE.txt
Requires-Dist: filelock (==3.0.12)
